simulator.cpython-311-i386-linux-gnu.so
qokit-0.1.3.dist-info/WHEEL
qokit-0.1.3.dist-info/LICENSE
qokit-0.1.3.dist-info/RECORD
qokit-0.1.3.dist-info/top_level.txt
qokit-0.1.3.dist-info/METADATA
examples/advanced/classical_solvers_for_LABS/run_cplex.py
examples/advanced/classical_solvers_for_LABS/run_gurobi.py
examples/advanced/classical_solvers_for_LABS/generate_lp_files.py
qokit/qaoa_circuit_labs.py
qokit/perf_utils.py
qokit/qaoa_circuit_maxcut.py
qokit/parameter_utils.py
qokit/generator.py
qokit/utils.py
qokit/dicke_state_utils.py
qokit/maxcut.py
qokit/__init__.py
qokit/qaoa_objective_labs.py
qokit/matrix.py
qokit/qaoa_objective.py
qokit/labs.py
qokit/qaoa_objective_portfolio.py
qokit/portfolio_optimization.py
qokit/qaoa_objective_maxcut.py
qokit/qaoa_circuit_portfolio.py
qokit/classical_methods/utils.py
qokit/classical_methods/__init__.py
qokit/classical_methods/generate_lp.py
qokit/fur/qaoa_simulator_base.py
qokit/fur/__init__.py
qokit/fur/lazy_import.py
qokit/fur/c/utils.py
qokit/fur/c/qaoa_simulator.py
qokit/fur/c/__init__.py
qokit/fur/c/gates.py
qokit/fur/c/csim/lib.py
qokit/fur/c/csim/__init__.py
qokit/fur/c/csim/libpath.py
qokit/fur/c/csim/wrapper.py
qokit/fur/python/qaoa_fur.py
qokit/fur/python/utils.py
qokit/fur/python/qaoa_simulator.py
qokit/fur/python/__init__.py
qokit/fur/python/fur.py
qokit/fur/python/gates.py
qokit/fur/mpi_nbcuda/compute_costs.py
qokit/fur/mpi_nbcuda/qaoa_fur.py
qokit/fur/mpi_nbcuda/qaoa_simulator.py
qokit/fur/mpi_nbcuda/__init__.py
qokit/fur/mpi_nbcuda/fur.py
qokit/fur/mpi_custatevec/__init__.py
qokit/fur/diagonal_precomputation/numpy_vectorized.py
qokit/fur/diagonal_precomputation/__init__.py
qokit/fur/diagonal_precomputation/gpu_numba.py
qokit/fur/nbcuda/qaoa_fur.py
qokit/fur/nbcuda/utils.py
qokit/fur/nbcuda/qaoa_simulator.py
qokit/fur/nbcuda/__init__.py
qokit/fur/nbcuda/fur.py
qokit/fur/nbcuda/gates.py
qokit/fur/nbcuda/diagonal.py
qokit/assets/__init__.py
qokit/assets/best_LABS_QAOA_parameters_wrt_overlap.json
qokit/assets/best_LABS_QAOA_parameters_wrt_MF.json
