Metadata-Version: 2.1
Name: qokit
Version: 0.1.3
Summary: Quantum Optimization Toolkit
Author: JP Morgan Chase & Co
Author-email: OmniQ_Support@jpmchase.com
License:                                  Apache License
Classifier: Development Status :: 2 - Pre-Alpha
Classifier: License :: OSI Approved :: Apache Software License
Classifier: Programming Language :: Python
Classifier: Operating System :: OS Independent
Classifier: Programming Language :: Python :: 3.9
Classifier: Programming Language :: Python :: 3.10
Classifier: Programming Language :: Python :: 3.11
Requires-Python: >=3.9.0
License-File: LICENSE
Requires-Dist: networkx>=3.0.0
Requires-Dist: importlib-resources>=5.2.2
Requires-Dist: numba<1,>=0.56.4
Requires-Dist: pandas>=2.0.1
Requires-Dist: pathos>=0.3.0
Requires-Dist: pytest>=7.3.1
Requires-Dist: pytket<2,>=1.15.0
Requires-Dist: pytket-qiskit<1,>=0.39.0
Requires-Dist: pytket-quantinuum<1,>=0.16.0
Requires-Dist: qiskit<1,>=0.42
Requires-Dist: qiskit-finance<1,>=0.3
Requires-Dist: qiskit-ibmq-provider<1,>=0.20.2
Requires-Dist: qiskit-terra<1,>=0.23.2
Requires-Dist: scipy>=1.10.1
Requires-Dist: seaborn>=0.12.2
Requires-Dist: sympy>=1.12
Requires-Dist: tqdm>=4.65.0
Provides-Extra: gpu
Requires-Dist: qiskit-aer-gpu>=0.8; extra == "gpu"
Provides-Extra: dev
Requires-Dist: black[d]>=23.3.0; extra == "dev"
Requires-Dist: setuptools>=58.1.0; extra == "dev"
Requires-Dist: Deprecated>=1.2.13; extra == "dev"
Requires-Dist: urllib3>=1.26.6; extra == "dev"
Requires-Dist: statsmodels>=0.13.5; extra == "dev"
Requires-Dist: scikit-learn>=1.2.2; extra == "dev"
Provides-Extra: solvers
Requires-Dist: docplex>=2.18.200; extra == "solvers"
Requires-Dist: gurobipy>=9.1.2; extra == "solvers"
